nnabla_nas/__init__.py
nnabla_nas/contrib/__init__.py
nnabla_nas/contrib/model.py
nnabla_nas/contrib/classification/__init__.py
nnabla_nas/contrib/classification/base.py
nnabla_nas/contrib/classification/misc.py
nnabla_nas/contrib/classification/darts/__init__.py
nnabla_nas/contrib/classification/darts/helper.py
nnabla_nas/contrib/classification/darts/modules.py
nnabla_nas/contrib/classification/darts/network.py
nnabla_nas/contrib/classification/fairnas/__init__.py
nnabla_nas/contrib/classification/fairnas/modules.py
nnabla_nas/contrib/classification/fairnas/network.py
nnabla_nas/contrib/classification/mobilenet/__init__.py
nnabla_nas/contrib/classification/mobilenet/helper.py
nnabla_nas/contrib/classification/mobilenet/modules.py
nnabla_nas/contrib/classification/mobilenet/network.py
nnabla_nas/contrib/classification/ofa/__init__.py
nnabla_nas/contrib/classification/pnas/__init__.py
nnabla_nas/contrib/classification/pnas/network.py
nnabla_nas/contrib/classification/random_wired/__init__.py
nnabla_nas/contrib/classification/random_wired/random_wired.py
nnabla_nas/contrib/classification/zoph/__init__.py
nnabla_nas/contrib/classification/zoph/zoph.py
nnabla_nas/contrib/common/__init__.py
nnabla_nas/contrib/common/ofa/__init__.py
nnabla_nas/contrib/common/ofa/layers.py
nnabla_nas/contrib/common/ofa/elastic_nn/__init__.py
nnabla_nas/contrib/common/ofa/elastic_nn/utils.py
nnabla_nas/contrib/common/ofa/elastic_nn/modules/__init__.py
nnabla_nas/contrib/common/ofa/elastic_nn/modules/dynamic_layers.py
nnabla_nas/contrib/common/ofa/elastic_nn/modules/dynamic_op.py
nnabla_nas/contrib/common/ofa/utils/__init__.py
nnabla_nas/contrib/common/ofa/utils/common_tools.py
nnabla_nas/contrib/common/ofa/utils/random_resize_crop.py
nnabla_nas/contrib/detection/__init__.py
nnabla_nas/contrib/segmentation/__init__.py
nnabla_nas/dataset/__init__.py
nnabla_nas/dataset/cifar10.py
nnabla_nas/dataset/csv.py
nnabla_nas/dataset/dataloader.py
nnabla_nas/dataset/imagenet.py
nnabla_nas-0.15.0.dist-info/LICENSE
nnabla_nas-0.15.0.dist-info/METADATA
nnabla_nas-0.15.0.dist-info/WHEEL
nnabla_nas-0.15.0.dist-info/entry_points.txt
nnabla_nas-0.15.0.dist-info/top_level.txt
nnabla_nas-0.15.0.dist-info/RECORD
