Metadata-Version: 2.1
Name: nnabla-nas
Version: 0.15.0
Summary: Use NNC compute resource from NNabla
Home-page: UNKNOWN
Author: UNKNOWN
Author-email: UNKNOWN
License: UNKNOWN
Keywords: deep learning artificial intelligence machine learning neural network
Platform: UNKNOWN
Classifier: Development Status :: 5 - Production/Stable
Classifier: Intended Audience :: Developers
Classifier: Intended Audience :: Education
Classifier: Intended Audience :: Science/Research
Classifier: Topic :: Scientific/Engineering
Classifier: Topic :: Scientific/Engineering :: Artificial Intelligence
Classifier: License :: OSI Approved :: Apache Software License
Classifier: Programming Language :: Python :: 3
Classifier: Programming Language :: Python :: 3.5
Classifier: Programming Language :: Python :: 3.6
Classifier: Programming Language :: Python :: 3.7
Classifier: Operating System :: POSIX :: Linux
Requires-Dist: graphviz
Requires-Dist: h5py
Requires-Dist: mako
Requires-Dist: mypy
Requires-Dist: networkx
Requires-Dist: nnabla
Requires-Dist: scikit-learn
Requires-Dist: tensorboard
Requires-Dist: tqdm
Requires-Dist: hydra-core
Requires-Dist: hydra-colorlog
Requires-Dist: more-itertools
